Metadata-Version: 2.1
Name: opexebo
Version: 0.7.2
Summary: Collection of python code in Kavli lab.
Home-page: https://github.com/kavli-ntnu/opexebo
Author: Simon Ball
Author-email: simon.ball@ntnu.no
License: UNKNOWN
Keywords: neuroscience kavli gridscore
Platform: UNKNOWN
Classifier: License :: OSI Approved :: MIT License
Classifier: Development Status :: 4 - Beta
Classifier: Intended Audience :: Developers
Classifier: Natural Language :: English
Classifier: Programming Language :: Python :: 3
Classifier: Programming Language :: Python :: 3.8
Classifier: Programming Language :: Python :: 3.9
Classifier: Programming Language :: Python :: 3.10
Classifier: Programming Language :: Python :: 3.11
Requires-Dist: astropy >=5.3
Requires-Dist: numpy >=1.24
Requires-Dist: scipy >=1.10
Requires-Dist: scikit-image >=0.19
Requires-Dist: opencv-python
Provides-Extra: full
Requires-Dist: sep >=1.2.1 ; extra == 'full'
